hkis.py
hkis-0.2.dist-info/METADATA
hkis-0.2.dist-info/WHEEL
hkis-0.2.dist-info/entry_points.txt
hkis-0.2.dist-info/top_level.txt
hkis-0.2.dist-info/RECORD
