Metadata-Version: 2.1
Name: hkis
Version: 0.2
Summary: HackInScience CLI client.
Home-page: https://framagit.org/hackinscience/hkis-website
Author: Julien Palard
Author-email: julien@palard.fr
License: MIT License
Platform: UNKNOWN
Requires-Python: >=3.7
Requires-Dist: tabulate
Requires-Dist: requests
Requires-Dist: websocket-client
